h7_logger_manager/__init__.py
h7_logger_manager/logger_manager.py
h7_logger_manager-1.0.0.dist-info/METADATA
h7_logger_manager-1.0.0.dist-info/WHEEL
h7_logger_manager-1.0.0.dist-info/top_level.txt
h7_logger_manager-1.0.0.dist-info/RECORD
