Metadata-Version: 2.4
Name: h7-logger-manager
Version: 1.0.0
Summary: Core utility classes for logging management in Python projects
Author-email: Roger Mori <roger.mori@example.com>
License: MIT
Project-URL: Homepage, https://github.com/rogermori/h7-logger-manager
Project-URL: Bug Tracker, https://github.com/rogermori/h7-logger-manager/issues
Classifier: Programming Language :: Python :: 3
Classifier: License :: OSI Approved :: MIT License
Classifier: Operating System :: OS Independent
Requires-Python: >=3.7
Requires-Dist: h7-file-finder>=1.0.0
Requires-Dist: h7-env-manager>=1.0.0
